numtogreek/__init__.py
numtogreek/numtogreek.py
numtogreek/data/CHANGELOG
numtogreek/data/README.rst
numtogreek/data/VERSION
numtogreek/data/gpl-3.0.txt
numtogreek-1.0.3.dist-info/DESCRIPTION.rst
numtogreek-1.0.3.dist-info/METADATA
numtogreek-1.0.3.dist-info/RECORD
numtogreek-1.0.3.dist-info/WHEEL
numtogreek-1.0.3.dist-info/metadata.json
numtogreek-1.0.3.dist-info/top_level.txt
