Metadata-Version: 2.0
Name: numtogreek
Version: 1.0.3
Summary: Converts Numbers (Integers and Floats) to Greek Words.
Home-page: https://bitbucket.org/kamar/numtogreek
Author: Konstas Marmatakis
Author-email: marmako@gmail.com
Maintainer: kamar
License: GNU General Public License v3 (GPLv3)
Keywords: numbers,convert,greek,words,convert number,greek words
Platform: Linux
Platform: Windows
Classifier: Development Status :: 5 - Production/Stable
Classifier: Environment :: Console
Classifier: Intended Audience :: Other Audience
Classifier: Intended Audience :: Developers
Classifier: License :: OSI Approved :: GNU General Public License v3 (GPLv3)
Classifier: Natural Language :: Greek
Classifier: Operating System :: Microsoft
Classifier: Operating System :: Microsoft :: Windows :: Windows 7
Classifier: Operating System :: Microsoft :: Windows :: Windows 8
Classifier: Operating System :: Microsoft :: Windows :: Windows 8.1
Classifier: Operating System :: POSIX
Classifier: Operating System :: POSIX :: Linux
Classifier: Programming Language :: Python :: 3
Classifier: Programming Language :: Python :: 3.3
Classifier: Programming Language :: Python :: 3.4
Classifier: Programming Language :: Python :: 3.5
Classifier: Programming Language :: Python :: 3.6
